randomRouteGenerator/__init__.py
randomRouteGenerator/coordinate.py
randomRouteGenerator/overpass_test.py
randomRouteGenerator/route.py
randomRouteGenerator/route_generator.py
random_route_generator-1.0.3.dist-info/LICENSE
random_route_generator-1.0.3.dist-info/METADATA
random_route_generator-1.0.3.dist-info/WHEEL
random_route_generator-1.0.3.dist-info/top_level.txt
random_route_generator-1.0.3.dist-info/zip-safe
random_route_generator-1.0.3.dist-info/RECORD
