Metadata-Version: 2.1
Name: random-route-generator
Version: 1.0.3
Summary: A Python libary to generate a random route with a specified length.
Home-page: https://github.com/oskarkraemer/randomRouteGenerator
Author: Oskar Kraemer
License: GPL-3.0
Keywords: geography,route,random,generator,gpx,gps
Classifier: Programming Language :: Python :: 3
Classifier: Operating System :: OS Independent
Classifier: Topic :: Software Development :: Libraries :: Python Modules
License-File: LICENSE
Requires-Dist: gpxpy >=1.5.0
Requires-Dist: overpy >=0.6
Requires-Dist: haversine >=2.7.0
